argsync/__init__.py
argsync/gdrive.py
argsync/main.py
argsync/pull.py
argsync/push.py
argsync-1.2.1.dist-info/LICENSE
argsync-1.2.1.dist-info/METADATA
argsync-1.2.1.dist-info/WHEEL
argsync-1.2.1.dist-info/entry_points.txt
argsync-1.2.1.dist-info/top_level.txt
argsync-1.2.1.dist-info/RECORD
